secrets_details
