Metadata-Version: 1.0
Name: secret-details
Version: 0.3.2
Summary: secret_details
Home-page: https://github.com/srgrn/secrets_details
Author: Eran Zimbler
Author-email: eranz@rumble.me
License: UNKNOWN
Platform: UNKNOWN
